lmc/__init__.py
lmc/lmc.py
lmc-0.2.2.dist-info/LICENSE
lmc-0.2.2.dist-info/METADATA
lmc-0.2.2.dist-info/WHEEL
lmc-0.2.2.dist-info/top_level.txt
lmc-0.2.2.dist-info/RECORD
