Metadata-Version: 2.1
Name: lmc
Version: 0.2.2
Summary: Logarithmantic Monte Carlo
Home-page: https://github.com/abmantz/lmc
Author: Adam Mantz
Author-email: amantz@slac.stanford.edu
License: LGPL-3.0
Classifier: Development Status :: 4 - Beta
Classifier: Intended Audience :: Science/Research
Classifier: License :: OSI Approved :: GNU Lesser General Public License v3 or later (LGPLv3+)
Classifier: Programming Language :: Python :: 2
Classifier: Programming Language :: Python :: 3
License-File: LICENSE
Requires-Dist: numpy
